tronlibpy/__init__.py
tronlibpy/main.py
tronlibpy-0.0.1.dist-info/LICENSE.txt
tronlibpy-0.0.1.dist-info/METADATA
tronlibpy-0.0.1.dist-info/WHEEL
tronlibpy-0.0.1.dist-info/top_level.txt
tronlibpy-0.0.1.dist-info/RECORD
