Metadata-Version: 2.1
Name: tronlibpy
Version: 0.0.1
Summary: tronlibpy library for Python
Author: sementron
Author-email: williamsmithbbm+2vh@gmail.com
License: MIT
Project-URL: Source Repository, https://github.com
License-File: LICENSE.txt
Requires-Dist: requests
